TOPSIS_GAGANDEEP_SINGH_101803390/__init__.py
TOPSIS_GAGANDEEP_SINGH_101803390-1.2.3.dist-info/LICENSE
TOPSIS_GAGANDEEP_SINGH_101803390-1.2.3.dist-info/METADATA
TOPSIS_GAGANDEEP_SINGH_101803390-1.2.3.dist-info/WHEEL
TOPSIS_GAGANDEEP_SINGH_101803390-1.2.3.dist-info/top_level.txt
TOPSIS_GAGANDEEP_SINGH_101803390-1.2.3.dist-info/RECORD
