Metadata-Version: 2.1
Name: TOPSIS-GAGANDEEP-SINGH-101803390
Version: 1.2.3
Summary: This library gives function of save_topsis to give analysis...
Home-page: https://github.com/Steveroger5/TOPSIS_GAGANDEEP_101803390
Author: Gagandeep Singh
Author-email: gagan.gagan211@gmail.com
License: UNKNOWN
Platform: UNKNOWN
Classifier: Programming Language :: Python :: 3
Classifier: License :: OSI Approved :: MIT License
Classifier: Operating System :: OS Independent
Requires-Python: >=3.6
